nystrom_attention/__init__.py
nystrom_attention/nystrom_attention.py
nystrom_attention-0.0.14.dist-info/licenses/LICENSE
nystrom_attention-0.0.14.dist-info/METADATA
nystrom_attention-0.0.14.dist-info/WHEEL
nystrom_attention-0.0.14.dist-info/top_level.txt
nystrom_attention-0.0.14.dist-info/RECORD
